omnifit/__init__.py
omnifit/_astropy_init.py
omnifit/conftest.py
omnifit/version.py
omnifit/data/waterice_absorption.txt
omnifit/data/waterice_nandk.txt
omnifit/data/watermethanol_absorption.txt
omnifit/fitter/__init__.py
omnifit/fitter/fitter.py
omnifit/fitter/functions.py
omnifit/fitter/tests/__init__.py
omnifit/fitter/tests/test_fitter.py
omnifit/spectrum/__init__.py
omnifit/spectrum/spectrum.py
omnifit/spectrum/tests/__init__.py
omnifit/spectrum/tests/test_spectrumcreation.py
omnifit/spectrum/tests/test_spectruminfo.py
omnifit/spectrum/tests/test_spectrummanipulation.py
omnifit/spectrum/tests/test_spectrumplotting.py
omnifit/tests/__init__.py
omnifit/tests/helpers.py
omnifit/utils/__init__.py
omnifit/utils/utils.py
omnifit/utils/tests/__init__.py
omnifit/utils/tests/test_kkrelation.py
omnifit/utils/tests/test_units.py
omnifit-0.3.0.dist-info/LICENSE.rst
omnifit-0.3.0.dist-info/METADATA
omnifit-0.3.0.dist-info/WHEEL
omnifit-0.3.0.dist-info/entry_points.txt
omnifit-0.3.0.dist-info/top_level.txt
omnifit-0.3.0.dist-info/RECORD
