Metadata-Version: 2.1
Name: omnifit
Version: 0.3.0
Summary: Omnifit - astronomical ice spectroscopy fitting
Home-page: https://github.com/RiceMunk/omnifit
Author: Aleksi Suutarinen
Author-email: aleksi.suutarinen@gmail.com
License: BSD 3-Clause
Platform: UNKNOWN
Requires-Python: >=3.7
License-File: licenses/LICENSE.rst
Requires-Dist: astropy (>=4.0)
Requires-Dist: numpy (>=1.13)
Requires-Dist: scipy
Requires-Dist: matplotlib
Requires-Dist: lmfit
Provides-Extra: docs
Requires-Dist: sphinx-astropy ; extra == 'docs'
Provides-Extra: test
Requires-Dist: pytest-astropy ; extra == 'test'
